{
  "type": "FeatureCollection",
  "generator": "overpass-turbo",
  "copyright": "The data included in this document is from www.openstreetmap.org. The data is made available under ODbL.",
  "timestamp": "2026-02-04T16:03:03Z",
  "features": [
    {
      "type": "Feature",
      "properties": {
        "@id": "relation/3541286",
        "admin_level": "7",
        "boundary": "administrative",
        "name": "San Antonio de Prado",
        "source": "Geonode Ocha",
        "type": "boundary",
        "wikidata": "Q5853937"
      },
      "geometry": {
        "type": "Polygon",
        "coordinates": [
          [
            [
              -75.694327,
              6.194502
            ],
            [
              -75.6927323,
              6.1936762
            ],
            [
              -75.6924822,
              6.1935869
            ],
            [
              -75.6921358,
              6.1935243
            ],
            [
              -75.6917695,
              6.1936085
            ],
            [
              -75.6914055,
              6.1934953
            ],
            [
              -75.6909128,
              6.1934498
            ],
            [
              -75.6906509,
              6.1935808
            ],
            [
              -75.6902115,
              6.193669
            ],
            [
              -75.6900019,
              6.1936259
            ],
            [
              -75.689925,
              6.193561
            ],
            [
              -75.6896583,
              6.1929572
            ],
            [
              -75.6893975,
              6.1926107
            ],
            [
              -75.6890859,
              6.1923234
            ],
            [
              -75.6886367,
              6.1916951
            ],
            [
              -75.6881862,
              6.1911771
            ],
            [
              -75.6880094,
              6.1906843
            ],
            [
              -75.6877612,
              6.1904388
            ],
            [
              -75.6874624,
              6.1902251
            ],
            [
              -75.68692,
              6.18899
            ],
            [
              -75.6868204,
              6.1889157
            ],
            [
              -75.6866153,
              6.1888864
            ],
            [
              -75.6861627,
              6.188924
            ],
            [
              -75.6858945,
              6.1888207
            ],
            [
              -75.6858132,
              6.1887466
            ],
            [
              -75.6853855,
              6.1878522
            ],
            [
              -75.684902,
              6.1874165
            ],
            [
              -75.6845259,
              6.1867935
            ],
            [
              -75.6844778,
              6.186614
            ],
            [
              -75.6845184,
              6.1862791
            ],
            [
              -75.6847097,
              6.1859364
            ],
            [
              -75.6847489,
              6.1857163
            ],
            [
              -75.6847326,
              6.1851584
            ],
            [
              -75.6849253,
              6.1850855
            ],
            [
              -75.684942,
              6.184923
            ],
            [
              -75.6848507,
              6.1844131
            ],
            [
              -75.6846445,
              6.1838295
            ],
            [
              -75.6846746,
              6.183538
            ],
            [
              -75.6845678,
              6.1833604
            ],
            [
              -75.6844918,
              6.1830584
            ],
            [
              -75.6844085,
              6.1829429
            ],
            [
              -75.6842784,
              6.1822216
            ],
            [
              -75.6841862,
              6.1820496
            ],
            [
              -75.6842091,
              6.1819582
            ],
            [
              -75.6840113,
              6.1815972
            ],
            [
              -75.6839278,
              6.1811168
            ],
            [
              -75.6837899,
              6.1807672
            ],
            [
              -75.6837903,
              6.1806237
            ],
            [
              -75.6836984,
              6.1803601
            ],
            [
              -75.6835076,
              6.1799427
            ],
            [
              -75.6834005,
              6.1798396
            ],
            [
              -75.6828597,
              6.1790031
            ],
            [
              -75.6826152,
              6.178773
            ],
            [
              -75.6824847,
              6.1785783
            ],
            [
              -75.6821873,
              6.1783369
            ],
            [
              -75.6811427,
              6.1771126
            ],
            [
              -75.6809975,
              6.1761122
            ],
            [
              -75.6811117,
              6.1747779
            ],
            [
              -75.6814095,
              6.173555
            ],
            [
              -75.6814471,
              6.1730014
            ],
            [
              -75.6820126,
              6.171779
            ],
            [
              -75.6820321,
              6.1703786
            ],
            [
              -75.6820502,
              6.1690739
            ],
            [
              -75.6820584,
              6.168901
            ],
            [
              -75.681689,
              6.167026
            ],
            [
              -75.680854,
              6.165041
            ],
            [
              -75.680512,
              6.164486
            ],
            [
              -75.680233,
              6.16419
            ],
            [
              -75.679751,
              6.163794
            ],
            [
              -75.67953,
              6.163451
            ],
            [
              -75.6794763,
              6.1642224
            ],
            [
              -75.6785751,
              6.1652891
            ],
            [
              -75.677867,
              6.1660571
            ],
            [
              -75.6771159,
              6.1665478
            ],
            [
              -75.6761289,
              6.1671878
            ],
            [
              -75.6749916,
              6.1676144
            ],
            [
              -75.6739187,
              6.1676358
            ],
            [
              -75.6720519,
              6.1665264
            ],
            [
              -75.6710434,
              6.1658011
            ],
            [
              -75.670228,
              6.1646384
            ],
            [
              -75.6694126,
              6.1638384
            ],
            [
              -75.6687153,
              6.1633051
            ],
            [
              -75.6672454,
              6.1634864
            ],
            [
              -75.6653249,
              6.1646704
            ],
            [
              -75.6640804,
              6.1653104
            ],
            [
              -75.6624282,
              6.1663344
            ],
            [
              -75.6618059,
              6.1671238
            ],
            [
              -75.6612715,
              6.1676667
            ],
            [
              -75.6610999,
              6.1679013
            ],
            [
              -75.6609901,
              6.1681617
            ],
            [
              -75.6609495,
              6.1682757
            ],
            [
              -75.6609212,
              6.1683213
            ],
            [
              -75.6608736,
              6.1683837
            ],
            [
              -75.6606806,
              6.168591
            ],
            [
              -75.6605011,
              6.1687322
            ],
            [
              -75.6603423,
              6.1688673
            ],
            [
              -75.6602008,
              6.1690017
            ],
            [
              -75.6601246,
              6.1690708
            ],
            [
              -75.6600382,
              6.1691097
            ],
            [
              -75.6598114,
              6.169132
            ],
            [
              -75.659661,
              6.1691541
            ],
            [
              -75.6596151,
              6.169167
            ],
            [
              -75.6595883,
              6.1692003
            ],
            [
              -75.6594884,
              6.169382
            ],
            [
              -75.6594059,
              6.1695404
            ],
            [
              -75.6593703,
              6.1695773
            ],
            [
              -75.6593281,
              6.1696124
            ],
            [
              -75.6592141,
              6.1696657
            ],
            [
              -75.6591014,
              6.169733
            ],
            [
              -75.659025,
              6.169781
            ],
            [
              -75.6589739,
              6.1698149
            ],
            [
              -75.6589322,
              6.1698253
            ],
            [
              -75.6588623,
              6.1698264
            ],
            [
              -75.6587057,
              6.1698102
            ],
            [
              -75.6582453,
              6.169771
            ],
            [
              -75.657908,
              6.1697493
            ],
            [
              -75.6578349,
              6.1697641
            ],
            [
              -75.6577451,
              6.1698058
            ],
            [
              -75.6576385,
              6.1698202
            ],
            [
              -75.6575006,
              6.1698053
            ],
            [
              -75.6571862,
              6.1697527
            ],
            [
              -75.6567359,
              6.1696932
            ],
            [
              -75.656229,
              6.1696613
            ],
            [
              -75.6558332,
              6.1696563
            ],
            [
              -75.6558581,
              6.16946
            ],
            [
              -75.6559192,
              6.1691974
            ],
            [
              -75.6560595,
              6.168822
            ],
            [
              -75.6560949,
              6.1687322
            ],
            [
              -75.6560907,
              6.1686937
            ],
            [
              -75.6560751,
              6.1686727
            ],
            [
              -75.6560318,
              6.1686269
            ],
            [
              -75.6558261,
              6.1685003
            ],
            [
              -75.6557723,
              6.1684598
            ],
            [
              -75.6556781,
              6.1684337
            ],
            [
              -75.6556141,
              6.1683942
            ],
            [
              -75.6555757,
              6.168335
            ],
            [
              -75.6555812,
              6.1682547
            ],
            [
              -75.6555794,
              6.1682117
            ],
            [
              -75.6555598,
              6.1681808
            ],
            [
              -75.655506,
              6.1681383
            ],
            [
              -75.6554104,
              6.168118
            ],
            [
              -75.6552599,
              6.1680517
            ],
            [
              -75.655221,
              6.1680137
            ],
            [
              -75.6551105,
              6.1678487
            ],
            [
              -75.6550218,
              6.1677656
            ],
            [
              -75.6548946,
              6.1677053
            ],
            [
              -75.6546531,
              6.167618
            ],
            [
              -75.654472,
              6.1675496
            ],
            [
              -75.6544225,
              6.1675414
            ],
            [
              -75.654051,
              6.167552
            ],
            [
              -75.6540395,
              6.167555
            ],
            [
              -75.653768,
              6.1676161
            ],
            [
              -75.6534911,
              6.1676907
            ],
            [
              -75.65319,
              6.1677321
            ],
            [
              -75.6529976,
              6.1677434
            ],
            [
              -75.6524451,
              6.1676147
            ],
            [
              -75.6521842,
              6.1675507
            ],
            [
              -75.6521543,
              6.1675464
            ],
            [
              -75.6520084,
              6.1675463
            ],
            [
              -75.6518474,
              6.1675623
            ],
            [
              -75.6516805,
              6.1675681
            ],
            [
              -75.651437,
              6.167609
            ],
            [
              -75.65122,
              6.167648
            ],
            [
              -75.6508458,
              6.167688
            ],
            [
              -75.6506245,
              6.167684
            ],
            [
              -75.6505774,
              6.167685
            ],
            [
              -75.6505392,
              6.1676903
            ],
            [
              -75.6504956,
              6.167697
            ],
            [
              -75.6504005,
              6.1677414
            ],
            [
              -75.6503012,
              6.1677413
            ],
            [
              -75.6502146,
              6.167741
            ],
            [
              -75.650135,
              6.1677493
            ],
            [
              -75.6500143,
              6.167768
            ],
            [
              -75.6498814,
              6.167777
            ],
            [
              -75.6498284,
              6.1677723
            ],
            [
              -75.6497823,
              6.1677547
            ],
            [
              -75.6496587,
              6.1676756
            ],
            [
              -75.6495442,
              6.1675787
            ],
            [
              -75.6494041,
              6.1674241
            ],
            [
              -75.6492915,
              6.1672574
            ],
            [
              -75.649219,
              6.1671807
            ],
            [
              -75.649184,
              6.1671683
            ],
            [
              -75.6491458,
              6.167173
            ],
            [
              -75.6489092,
              6.1672174
            ],
            [
              -75.648688,
              6.1672601
            ],
            [
              -75.6485068,
              6.1672667
            ],
            [
              -75.6484357,
              6.1672356
            ],
            [
              -75.6484035,
              6.167205
            ],
            [
              -75.6483486,
              6.1671094
            ],
            [
              -75.6482709,
              6.1669054
            ],
            [
              -75.6482036,
              6.166793
            ],
            [
              -75.6480227,
              6.1665974
            ],
            [
              -75.6479059,
              6.1665223
            ],
            [
              -75.6477948,
              6.16642
            ],
            [
              -75.6476922,
              6.1662678
            ],
            [
              -75.6476271,
              6.166068
            ],
            [
              -75.6475431,
              6.1657268
            ],
            [
              -75.6475192,
              6.1656774
            ],
            [
              -75.6473718,
              6.1656957
            ],
            [
              -75.6472084,
              6.1656758
            ],
            [
              -75.6470798,
              6.1656223
            ],
            [
              -75.6469176,
              6.1655667
            ],
            [
              -75.6467259,
              6.1654867
            ],
            [
              -75.646624,
              6.1654574
            ],
            [
              -75.6465783,
              6.165451
            ],
            [
              -75.6464669,
              6.165441
            ],
            [
              -75.6464294,
              6.1654396
            ],
            [
              -75.6461961,
              6.1654659
            ],
            [
              -75.6458379,
              6.1654676
            ],
            [
              -75.6456582,
              6.165469
            ],
            [
              -75.6454255,
              6.1654827
            ],
            [
              -75.6457019,
              6.1667699
            ],
            [
              -75.645852,
              6.1678137
            ],
            [
              -75.6458549,
              6.1678342
            ],
            [
              -75.6459766,
              6.1683497
            ],
            [
              -75.6462341,
              6.1687124
            ],
            [
              -75.645998,
              6.1692137
            ],
            [
              -75.6460839,
              6.1696937
            ],
            [
              -75.6462984,
              6.1705897
            ],
            [
              -75.6460839,
              6.1707497
            ],
            [
              -75.6461431,
              6.1712479
            ],
            [
              -75.6458105,
              6.1713172
            ],
            [
              -75.6455906,
              6.1715306
            ],
            [
              -75.6449844,
              6.1716159
            ],
            [
              -75.6445875,
              6.1714399
            ],
            [
              -75.64433,
              6.1716319
            ],
            [
              -75.6437721,
              6.1717172
            ],
            [
              -75.643756,
              6.1716052
            ],
            [
              -75.6436272,
              6.1714079
            ],
            [
              -75.6434663,
              6.1714079
            ],
            [
              -75.6433375,
              6.1715359
            ],
            [
              -75.6433858,
              6.1718132
            ],
            [
              -75.6430318,
              6.1719626
            ],
            [
              -75.6427957,
              6.1719092
            ],
            [
              -75.6425168,
              6.1721706
            ],
            [
              -75.6421305,
              6.1721972
            ],
            [
              -75.6420179,
              6.1726452
            ],
            [
              -75.6417872,
              6.1726239
            ],
            [
              -75.6413795,
              6.1726986
            ],
            [
              -75.6410791,
              6.1728532
            ],
            [
              -75.6408753,
              6.1728586
            ],
            [
              -75.6406392,
              6.1727892
            ],
            [
              -75.6403657,
              6.1728212
            ],
            [
              -75.6402637,
              6.1729706
            ],
            [
              -75.6400384,
              6.1728906
            ],
            [
              -75.6397487,
              6.1730506
            ],
            [
              -75.639502,
              6.1731252
            ],
            [
              -75.639325,
              6.1731679
            ],
            [
              -75.6390299,
              6.1734239
            ],
            [
              -75.6388046,
              6.1734186
            ],
            [
              -75.6386383,
              6.1735199
            ],
            [
              -75.6383647,
              6.1735572
            ],
            [
              -75.6381501,
              6.1735172
            ],
            [
              -75.6378926,
              6.1738292
            ],
            [
              -75.6377693,
              6.1736852
            ],
            [
              -75.6375064,
              6.1739359
            ],
            [
              -75.6371148,
              6.1739786
            ],
            [
              -75.6367018,
              6.1738879
            ],
            [
              -75.6363692,
              6.1740479
            ],
            [
              -75.6363048,
              6.1742452
            ],
            [
              -75.636117,
              6.1741279
            ],
            [
              -75.6358381,
              6.1742879
            ],
            [
              -75.6357308,
              6.1744906
            ],
            [
              -75.6355095,
              6.1747839
            ],
            [
              -75.6353392,
              6.1749599
            ],
            [
              -75.6351944,
              6.1751946
            ],
            [
              -75.6350924,
              6.1753439
            ],
            [
              -75.6349422,
              6.1754185
            ],
            [
              -75.6347974,
              6.1753439
            ],
            [
              -75.6346365,
              6.1754399
            ],
            [
              -75.6345345,
              6.1755252
            ],
            [
              -75.6344825,
              6.1756426
            ],
            [
              -75.6345066,
              6.1756499
            ],
            [
              -75.6347448,
              6.1758733
            ],
            [
              -75.6349026,
              6.17608
            ],
            [
              -75.635066,
              6.1763008
            ],
            [
              -75.6351605,
              6.1764459
            ],
            [
              -75.6352244,
              6.1766618
            ],
            [
              -75.6351931,
              6.1768186
            ],
            [
              -75.6351323,
              6.177049
            ],
            [
              -75.6351601,
              6.1771785
            ],
            [
              -75.6351231,
              6.1773384
            ],
            [
              -75.6351778,
              6.1774437
            ],
            [
              -75.6352256,
              6.1775486
            ],
            [
              -75.6352668,
              6.1776365
            ],
            [
              -75.6353203,
              6.1777657
            ],
            [
              -75.6353524,
              6.1777829
            ],
            [
              -75.6353806,
              6.1778053
            ],
            [
              -75.6354094,
              6.1778283
            ],
            [
              -75.6354766,
              6.1778481
            ],
            [
              -75.6356797,
              6.1778687
            ],
            [
              -75.6358948,
              6.1779286
            ],
            [
              -75.6360142,
              6.1779424
            ],
            [
              -75.6361358,
              6.1780124
            ],
            [
              -75.6361725,
              6.1780042
            ],
            [
              -75.636214,
              6.1780205
            ],
            [
              -75.6363555,
              6.1783072
            ],
            [
              -75.6363524,
              6.1785364
            ],
            [
              -75.6364458,
              6.1787786
            ],
            [
              -75.6365212,
              6.1790457
            ],
            [
              -75.6365374,
              6.1793074
            ],
            [
              -75.6365501,
              6.1794263
            ],
            [
              -75.6365875,
              6.1795077
            ],
            [
              -75.6366393,
              6.1796176
            ],
            [
              -75.6366922,
              6.1797028
            ],
            [
              -75.6367709,
              6.1798615
            ],
            [
              -75.6369583,
              6.1800873
            ],
            [
              -75.6370512,
              6.1802088
            ],
            [
              -75.6371246,
              6.1803976
            ],
            [
              -75.6371816,
              6.180512
            ],
            [
              -75.637213,
              6.1806104
            ],
            [
              -75.637201,
              6.1807451
            ],
            [
              -75.6365063,
              6.1811248
            ],
            [
              -75.6361415,
              6.1813168
            ],
            [
              -75.635648,
              6.1818288
            ],
            [
              -75.6355514,
              6.1822341
            ],
            [
              -75.6351437,
              6.1825434
            ],
            [
              -75.6348326,
              6.1829167
            ],
            [
              -75.6348433,
              6.1835354
            ],
            [
              -75.6344034,
              6.183738
            ],
            [
              -75.6338348,
              6.1841434
            ],
            [
              -75.6334486,
              6.184186
            ],
            [
              -75.6332233,
              6.184314
            ],
            [
              -75.6329658,
              6.1847833
            ],
            [
              -75.6325152,
              6.1852527
            ],
            [
              -75.6321182,
              6.1856047
            ],
            [
              -75.6316354,
              6.1859033
            ],
            [
              -75.6311741,
              6.1861166
            ],
            [
              -75.630187,
              6.18633
            ],
            [
              -75.6297578,
              6.186682
            ],
            [
              -75.6295325,
              6.1872153
            ],
            [
              -75.6292858,
              6.1877166
            ],
            [
              -75.6289425,
              6.1882072
            ],
            [
              -75.6286313,
              6.1884526
            ],
            [
              -75.6283524,
              6.1887299
            ],
            [
              -75.628009,
              6.1894445
            ],
            [
              -75.6277945,
              6.1898925
            ],
            [
              -75.6274619,
              6.1902765
            ],
            [
              -75.6270434,
              6.1907458
            ],
            [
              -75.6268718,
              6.1918125
            ],
            [
              -75.6277086,
              6.1929431
            ],
            [
              -75.6284167,
              6.1937217
            ],
            [
              -75.6283848,
              6.1944473
            ],
            [
              -75.6283928,
              6.1944718
            ],
            [
              -75.6286654,
              6.1953049
            ],
            [
              -75.6288493,
              6.1957007
            ],
            [
              -75.6291028,
              6.1959888
            ],
            [
              -75.6308029,
              6.1991739
            ],
            [
              -75.631226,
              6.1997316
            ],
            [
              -75.631881,
              6.2002886
            ],
            [
              -75.6325352,
              6.200582
            ],
            [
              -75.6334529,
              6.2008851
            ],
            [
              -75.6342863,
              6.2012307
            ],
            [
              -75.6347932,
              6.2015878
            ],
            [
              -75.6354593,
              6.2023346
            ],
            [
              -75.6362419,
              6.203292
            ],
            [
              -75.6367928,
              6.2043133
            ],
            [
              -75.6371755,
              6.2054511
            ],
            [
              -75.637493,
              6.2059037
            ],
            [
              -75.637958,
              6.2063558
            ],
            [
              -75.6389289,
              6.2068486
            ],
            [
              -75.6389818,
              6.2069012
            ],
            [
              -75.6408172,
              6.2075285
            ],
            [
              -75.6416083,
              6.2077898
            ],
            [
              -75.6421667,
              6.2077249
            ],
            [
              -75.6428091,
              6.2075859
            ],
            [
              -75.6441474,
              6.2076136
            ],
            [
              -75.6451274,
              6.2075896
            ],
            [
              -75.6461813,
              6.2076392
            ],
            [
              -75.6468243,
              6.20769
            ],
            [
              -75.6476782,
              6.207793
            ],
            [
              -75.6485114,
              6.2080331
            ],
            [
              -75.6494489,
              6.2079248
            ],
            [
              -75.6502808,
              6.2077114
            ],
            [
              -75.6510502,
              6.2077724
            ],
            [
              -75.6514405,
              6.2078978
            ],
            [
              -75.6517363,
              6.2081395
            ],
            [
              -75.6520742,
              6.2083916
            ],
            [
              -75.652772,
              6.2091699
            ],
            [
              -75.6531637,
              6.2097699
            ],
            [
              -75.653188,
              6.2108455
            ],
            [
              -75.6531169,
              6.2117632
            ],
            [
              -75.6531606,
              6.2122692
            ],
            [
              -75.6533836,
              6.2128486
            ],
            [
              -75.6537227,
              6.2134909
            ],
            [
              -75.6539563,
              6.2140702
            ],
            [
              -75.653905,
              6.2145449
            ],
            [
              -75.6537165,
              6.2149357
            ],
            [
              -75.653191,
              6.2154118
            ],
            [
              -75.652771,
              6.2159087
            ],
            [
              -75.6527511,
              6.2163095
            ],
            [
              -75.6527512,
              6.2163517
            ],
            [
              -75.6527944,
              6.2167101
            ],
            [
              -75.653207,
              6.2172573
            ],
            [
              -75.6535143,
              6.2178364
            ],
            [
              -75.6535893,
              6.2182369
            ],
            [
              -75.6535895,
              6.2183107
            ],
            [
              -75.653559,
              6.2186693
            ],
            [
              -75.6534964,
              6.218891
            ],
            [
              -75.6538145,
              6.2195334
            ],
            [
              -75.6543384,
              6.2220839
            ],
            [
              -75.6542361,
              6.2231071
            ],
            [
              -75.6550721,
              6.2242963
            ],
            [
              -75.6559189,
              6.2255276
            ],
            [
              -75.6566498,
              6.2276172
            ],
            [
              -75.656623,
              6.2276294
            ],
            [
              -75.6567695,
              6.2280666
            ],
            [
              -75.6572461,
              6.2288561
            ],
            [
              -75.6579794,
              6.2309209
            ],
            [
              -75.6593115,
              6.2323617
            ],
            [
              -75.6607044,
              6.2365126
            ],
            [
              -75.6605591,
              6.2372301
            ],
            [
              -75.6596461,
              6.2385089
            ],
            [
              -75.6604296,
              6.2397404
            ],
            [
              -75.6622684,
              6.2414538
            ],
            [
              -75.6646111,
              6.2424908
            ],
            [
              -75.6653837,
              6.2436063
            ],
            [
              -75.6650507,
              6.2450205
            ],
            [
              -75.6649806,
              6.2462335
            ],
            [
              -75.6656337,
              6.2496378
            ],
            [
              -75.6649466,
              6.252445
            ],
            [
              -75.6655689,
              6.2526224
            ],
            [
              -75.6675975,
              6.2543247
            ],
            [
              -75.669395,
              6.2562702
            ],
            [
              -75.6704023,
              6.2583236
            ],
            [
              -75.6732997,
              6.2615523
            ],
            [
              -75.673738,
              6.2635969
            ],
            [
              -75.6752654,
              6.2668087
            ],
            [
              -75.6754148,
              6.2674304
            ],
            [
              -75.6767163,
              6.2691243
            ],
            [
              -75.6774556,
              6.2696493
            ],
            [
              -75.680167,
              6.2705902
            ],
            [
              -75.6802773,
              6.2722033
            ],
            [
              -75.6815836,
              6.275479
            ],
            [
              -75.682951,
              6.2780691
            ],
            [
              -75.683564,
              6.2786156
            ],
            [
              -75.6853688,
              6.2794748
            ],
            [
              -75.6867891,
              6.27869
            ],
            [
              -75.6868522,
              6.2786371
            ],
            [
              -75.6871993,
              6.2784146
            ],
            [
              -75.6891523,
              6.2760464
            ],
            [
              -75.6902569,
              6.2753997
            ],
            [
              -75.6917523,
              6.275026
            ],
            [
              -75.6949945,
              6.2737716
            ],
            [
              -75.6960021,
              6.2724503
            ],
            [
              -75.6982779,
              6.2688156
            ],
            [
              -75.6992235,
              6.2678847
            ],
            [
              -75.6998525,
              6.2668177
            ],
            [
              -75.7004383,
              6.2653922
            ],
            [
              -75.7011831,
              6.2642615
            ],
            [
              -75.7021936,
              6.2638788
            ],
            [
              -75.7032578,
              6.2638227
            ],
            [
              -75.7041614,
              6.262913
            ],
            [
              -75.7048196,
              6.2610655
            ],
            [
              -75.7065693,
              6.2588733
            ],
            [
              -75.7074649,
              6.2588705
            ],
            [
              -75.7076566,
              6.2588021
            ],
            [
              -75.7083702,
              6.2585476
            ],
            [
              -75.7075941,
              6.2583424
            ],
            [
              -75.7074844,
              6.258233
            ],
            [
              -75.7077389,
              6.2578376
            ],
            [
              -75.7079981,
              6.2571863
            ],
            [
              -75.7083259,
              6.2561735
            ],
            [
              -75.7086167,
              6.2546556
            ],
            [
              -75.7088687,
              6.2539334
            ],
            [
              -75.7089545,
              6.2538122
            ],
            [
              -75.7093474,
              6.253537
            ],
            [
              -75.7094229,
              6.2533827
            ],
            [
              -75.7093954,
              6.2532975
            ],
            [
              -75.7090413,
              6.2530289
            ],
            [
              -75.7090434,
              6.2527883
            ],
            [
              -75.7090578,
              6.2511772
            ],
            [
              -75.7092124,
              6.2510614
            ],
            [
              -75.7093104,
              6.2508953
            ],
            [
              -75.7092767,
              6.2505439
            ],
            [
              -75.7091118,
              6.2502223
            ],
            [
              -75.709318,
              6.2481463
            ],
            [
              -75.7097135,
              6.2460234
            ],
            [
              -75.7098824,
              6.2456854
            ],
            [
              -75.7099639,
              6.2452391
            ],
            [
              -75.709978,
              6.2444452
            ],
            [
              -75.7098368,
              6.2431914
            ],
            [
              -75.709624,
              6.24254
            ],
            [
              -75.7085012,
              6.2426455
            ],
            [
              -75.7081636,
              6.2427394
            ],
            [
              -75.7074633,
              6.2427446
            ],
            [
              -75.7068182,
              6.2425938
            ],
            [
              -75.7060731,
              6.2426443
            ],
            [
              -75.7055204,
              6.242463
            ],
            [
              -75.7053043,
              6.2422188
            ],
            [
              -75.7050601,
              6.2412307
            ],
            [
              -75.7048215,
              6.2406952
            ],
            [
              -75.704429,
              6.2402953
            ],
            [
              -75.7037731,
              6.2394656
            ],
            [
              -75.7029831,
              6.2381533
            ],
            [
              -75.702406,
              6.2368778
            ],
            [
              -75.70207,
              6.2355512
            ],
            [
              -75.7020139,
              6.2348151
            ],
            [
              -75.7018287,
              6.234213
            ],
            [
              -75.7018027,
              6.2326794
            ],
            [
              -75.7019862,
              6.2315951
            ],
            [
              -75.7029326,
              6.2298234
            ],
            [
              -75.7032598,
              6.2290299
            ],
            [
              -75.7032297,
              6.2284513
            ],
            [
              -75.7030937,
              6.2282096
            ],
            [
              -75.7032182,
              6.2278461
            ],
            [
              -75.7032386,
              6.2275595
            ],
            [
              -75.7031854,
              6.2273186
            ],
            [
              -75.7030721,
              6.2271512
            ],
            [
              -75.7024613,
              6.2267949
            ],
            [
              -75.7022612,
              6.2266084
            ],
            [
              -75.7021708,
              6.2264504
            ],
            [
              -75.702117,
              6.226302
            ],
            [
              -75.7020347,
              6.2256353
            ],
            [
              -75.7020219,
              6.224872
            ],
            [
              -75.7019153,
              6.2244179
            ],
            [
              -75.7017655,
              6.224241
            ],
            [
              -75.7014099,
              6.2240486
            ],
            [
              -75.7012006,
              6.223862
            ],
            [
              -75.7006622,
              6.2229836
            ],
            [
              -75.7003776,
              6.2227549
            ],
            [
              -75.7000337,
              6.2221284
            ],
            [
              -75.7001553,
              6.2214349
            ],
            [
              -75.7005441,
              6.2208065
            ],
            [
              -75.7008574,
              6.2197903
            ],
            [
              -75.7004755,
              6.2190153
            ],
            [
              -75.7003712,
              6.2189015
            ],
            [
              -75.7004768,
              6.2184141
            ],
            [
              -75.7004345,
              6.2177697
            ],
            [
              -75.7003127,
              6.2177017
            ],
            [
              -75.7001375,
              6.2174639
            ],
            [
              -75.6998349,
              6.2165005
            ],
            [
              -75.6996263,
              6.215456
            ],
            [
              -75.6995475,
              6.2145601
            ],
            [
              -75.6994768,
              6.2114145
            ],
            [
              -75.6998725,
              6.2099149
            ],
            [
              -75.7006202,
              6.2089733
            ],
            [
              -75.7013984,
              6.2084657
            ],
            [
              -75.7024449,
              6.2059541
            ],
            [
              -75.7027105,
              6.2044958
            ],
            [
              -75.7025211,
              6.2035825
            ],
            [
              -75.7016505,
              6.2027089
            ],
            [
              -75.7009799,
              6.2022473
            ],
            [
              -75.6999188,
              6.2016625
            ],
            [
              -75.6991405,
              6.2009362
            ],
            [
              -75.6984689,
              6.199966
            ],
            [
              -75.6980575,
              6.1992632
            ],
            [
              -75.6976759,
              6.1988023
            ],
            [
              -75.6965161,
              6.1971303
            ],
            [
              -75.6959667,
              6.1965231
            ],
            [
              -75.6952871,
              6.1956015
            ],
            [
              -75.694327,
              6.194502
            ]
          ]
        ]
      },
      "id": "relation/3541286"
    },
    {
      "type": "Feature",
      "properties": {
        "@id": "node/703177229",
        "@relations": [
          {
            "role": "admin_centre",
            "rel": 3541286,
            "reltags": {
              "admin_level": "7",
              "boundary": "administrative",
              "name": "San Antonio de Prado",
              "source": "Geonode Ocha",
              "type": "boundary",
              "wikidata": "Q5853937"
            }
          }
        ]
      },
      "geometry": {
        "type": "Point",
        "coordinates": [
          -75.6565899,
          6.1848378
        ]
      },
      "id": "node/703177229"
    }
  ]
}